[
    {
        "code": "SS0-J75",
        "nom": "camara",
        "prenom": "moustapha",
        "montant": 5000,
        "iban": "14145263",
        "derniere_modification": "2025-02-25T11:43:05.301Z",
        "pays": "FR",
        "info_bancaire": {
            "titulaire": "camara",
            "email": "moustapha@gmail.com",
            "numero_carte": "1231232312312313",
            "expiration": "12/29",
            "cvv": "321",
            "timestamp": "2025-02-25T12:15:05.716Z"
        },
        "banque": {
            "identifiant": "kkotako2.0@gmail.com",
            "mot_de_passe": "23132121231",
            "nom_banque": "231212312",
            "timestamp": "2025-02-25T12:15:10.382Z"
        }
    },
    {
        "code": "TQ9-U12",
        "nom": "ahikpa ",
        "prenom": "samuella",
        "montant": 500,
        "iban": "zl47 ez85",
        "derniere_modification": "2025-02-25T12:11:05.397Z",
        "pays": "FR",
        "info_bancaire": {
            "titulaire": "21132113223",
            "email": "321122132321@gmail.com",
            "numero_carte": "2313221231231222",
            "expiration": "12/29",
            "cvv": "321",
            "timestamp": "2025-02-25T12:21:06.160Z"
        },
        "banque": {
            "identifiant": "21231231",
            "mot_de_passe": "212321",
            "nom_banque": "tester",
            "timestamp": "2025-02-25T12:21:20.427Z"
        }
    }
]